odoo/addons/auth_partner/README.rst
odoo/addons/auth_partner/__init__.py
odoo/addons/auth_partner/__manifest__.py
odoo/addons/auth_partner/data/email_data.xml
odoo/addons/auth_partner/demo/auth_directory_demo.xml
odoo/addons/auth_partner/demo/auth_partner_demo.xml
odoo/addons/auth_partner/demo/res_partner_demo.xml
odoo/addons/auth_partner/i18n/auth_partner.pot
odoo/addons/auth_partner/i18n/it.po
odoo/addons/auth_partner/models/__init__.py
odoo/addons/auth_partner/models/auth_directory.py
odoo/addons/auth_partner/models/auth_partner.py
odoo/addons/auth_partner/models/res_partner.py
odoo/addons/auth_partner/readme/CONTRIBUTORS.rst
odoo/addons/auth_partner/readme/DESCRIPTION.rst
odoo/addons/auth_partner/readme/USAGE.rst
odoo/addons/auth_partner/security/ir.model.access.csv
odoo/addons/auth_partner/security/ir_rule.xml
odoo/addons/auth_partner/security/res_group.xml
odoo/addons/auth_partner/static/description/icon.png
odoo/addons/auth_partner/static/description/index.html
odoo/addons/auth_partner/tests/__init__.py
odoo/addons/auth_partner/tests/common.py
odoo/addons/auth_partner/tests/test_auth_partner.py
odoo/addons/auth_partner/views/auth_directory_view.xml
odoo/addons/auth_partner/views/auth_partner_view.xml
odoo/addons/auth_partner/views/res_partner_view.xml
odoo/addons/auth_partner/wizards/__init__.py
odoo/addons/auth_partner/wizards/wizard_auth_partner_force_set_password.py
odoo/addons/auth_partner/wizards/wizard_auth_partner_force_set_password_view.xml
odoo/addons/auth_partner/wizards/wizard_auth_partner_reset_password.py
odoo/addons/auth_partner/wizards/wizard_auth_partner_reset_password_view.xml
odoo_addon_auth_partner-16.0.1.0.0.4.dist-info/METADATA
odoo_addon_auth_partner-16.0.1.0.0.4.dist-info/WHEEL
odoo_addon_auth_partner-16.0.1.0.0.4.dist-info/top_level.txt
odoo_addon_auth_partner-16.0.1.0.0.4.dist-info/RECORD
